Metadata-Version: 2.1
Name: odoo-addon-url-attachment-search-fuzzy
Version: 16.0.1.0.0.2
Summary: Fuzzy Search of URL in Attachments
Home-page: https://github.com/OCA/server-tools
Author: ForgeFlow, Odoo Community Association (OCA)
Author-email: support@odoo-community.org
License: AGPL-3
Platform: UNKNOWN
Classifier: Programming Language :: Python
Classifier: Framework :: Odoo
Classifier: Framework :: Odoo :: 16.0
Classifier: License :: OSI Approved :: GNU Affero General Public License v3
Requires-Python: >=3.10
Requires-Dist: odoo-addon-base-search-fuzzy <16.1dev,>=16.0dev
Requires-Dist: odoo <16.1dev,>=16.0a
